api/__init__.py
api/auth/__init__.py
api/auth/endpoints.py
api/users/__init__.py
api/users/api.py
api/users/endpoints.py
api/users/serializers.py
users/__init__.py
users/admin.py
users/apps.py
users/models.py
users/tests.py
users/views.py
users/migrations/0001_initial.py
users/migrations/0002_user_mbank_number.py
users/migrations/__init__.py
utils/__init__.py
utils/fields.py
utils/models.py
utils/serializers.py
utils/utils.py
django_rest_framework_auth_verify-0.0.3.dist-info/METADATA
django_rest_framework_auth_verify-0.0.3.dist-info/WHEEL
django_rest_framework_auth_verify-0.0.3.dist-info/top_level.txt
django_rest_framework_auth_verify-0.0.3.dist-info/RECORD
